sando/__init__.py
sando-0.0.0.dist-info/METADATA
sando-0.0.0.dist-info/WHEEL
sando-0.0.0.dist-info/top_level.txt
sando-0.0.0.dist-info/RECORD
