Metadata-Version: 2.4
Name: sando
Version: 0.0.0
Summary: Coming soon
Author-email: James Xu <james.xu@berkeley.edu>
